odoo/addons/fieldservice_sale_stock/README.rst
odoo/addons/fieldservice_sale_stock/__init__.py
odoo/addons/fieldservice_sale_stock/__manifest__.py
odoo/addons/fieldservice_sale_stock/i18n/es.po
odoo/addons/fieldservice_sale_stock/i18n/es_CL.po
odoo/addons/fieldservice_sale_stock/i18n/fieldservice_sale_stock.pot
odoo/addons/fieldservice_sale_stock/i18n/pt_BR.po
odoo/addons/fieldservice_sale_stock/models/__init__.py
odoo/addons/fieldservice_sale_stock/models/sale_order.py
odoo/addons/fieldservice_sale_stock/readme/CONFIGURE.rst
odoo/addons/fieldservice_sale_stock/readme/CONTRIBUTORS.rst
odoo/addons/fieldservice_sale_stock/readme/DESCRIPTION.rst
odoo/addons/fieldservice_sale_stock/readme/INSTALL.rst
odoo/addons/fieldservice_sale_stock/readme/ROADMAP.rst
odoo/addons/fieldservice_sale_stock/readme/USAGE.rst
odoo/addons/fieldservice_sale_stock/static/description/icon.png
odoo/addons/fieldservice_sale_stock/static/description/index.html
odoo12_addon_fieldservice_sale_stock-12.0.1.0.4.dist-info/METADATA
odoo12_addon_fieldservice_sale_stock-12.0.1.0.4.dist-info/WHEEL
odoo12_addon_fieldservice_sale_stock-12.0.1.0.4.dist-info/top_level.txt
odoo12_addon_fieldservice_sale_stock-12.0.1.0.4.dist-info/RECORD
